marple/__init__.py
marple/db.py
marple/files.py
marple/insight.py
marple/py.typed
marpledata-2.3.0.dist-info/METADATA
marpledata-2.3.0.dist-info/WHEEL
marpledata-2.3.0.dist-info/licenses/LICENSE
marpledata-2.3.0.dist-info/RECORD
