Metadata-Version: 2.4
Name: marpledata
Version: 2.3.0
Summary: Marple SDK for Python
Project-URL: Homepage, https://www.marpledata.com/
Project-URL: Documentation, https://docs.marpledata.com/docs
Project-URL: Repository, https://gitlab.com/marpledata/marple-sdk/-/tree/main/python
Project-URL: Issues, https://github.com/marpledata/marple-sdk/issues
Author-email: Matthias Baert <support@marpledata.com>, Jan Scheers <jan@marpledata.com>
License-Expression: Apache-2.0
License-File: LICENSE
Classifier: Development Status :: 4 - Beta
Classifier: Intended Audience :: Manufacturing
Classifier: Intended Audience :: Science/Research
Classifier: License :: OSI Approved :: Apache Software License
Classifier: Operating System :: OS Independent
Classifier: Programming Language :: Python :: 3
Classifier: Programming Language :: Python :: 3.11
Classifier: Programming Language :: Python :: 3.12
Classifier: Programming Language :: Python :: 3.13
Classifier: Programming Language :: Python :: 3.14
Classifier: Topic :: Scientific/Engineering
Requires-Python: <4.0,>=3.11
Requires-Dist: numpy>=2.3.5
Requires-Dist: pandas>=2.3.3
Requires-Dist: pyarrow>=22.0.0
Requires-Dist: requests>=2.32.5
